{
  "version": 4,
  "homepages": {
    "Main Homepage": {
      "value": "",
      "kind": "Graph view",
      "openOnStartup": true,
      "openMode": "Replace all open notes",
      "manualOpenMode": "Replace last note",
      "view": "Default view",
      "revertView": true,
      "openWhenEmpty": true,
      "refreshDataview": false,
      "autoCreate": false,
      "autoScroll": false,
      "pin": false,
      "commands": [],
      "alwaysApply": false,
      "hideReleaseNotes": false
    }
  },
  "separateMobile": false
}